# 错题集1

#### 下面几个关于Java里queue的说法哪些是正确的？（）
A. LinkedBlockingQueue开始一个可选有界队列，不允许null值。

B. PriorityQueue, LinkedBlockingQueue都是线程不安全的

C. PriorityQueue是一个无界队列，不允许null值，入队和出队的时间复杂度是(log(n))

D. PriorityQueue，ConcurrentLinkedQueue都遵循FIFO原则。

**答案**：AB
**题目来源**：https://www.nowcoder.com/profile/848042/myFollowings/detail/4016527

**解析**: 以下来自Java 8翻译：

1. `LinkedBlockingQueue`：基于链接节点的可选限定的blocking queue 。 这个队列排列元素FIFO（先进先出）。 队列的头部是队列中最长的元素。 队列的尾部是队列中最短时间的元素。 新元素插入队列的尾部，队列检索操作获取队列头部的元素。 链接队列通常具有比基于阵列的队列更高的吞吐量，但在大多数并发应用程序中的可预测性能较低。
`blocking queue`：不接受null元素；可能是容量有限的；实现被设计为主要用于生产者 - 消费者队列；不支持任何类型的“关闭”或“关闭”操作，表示不再添加项目实现是线程安全的；
2. `PriorityQueue`
  2.1、基于优先级堆的无限优先级queue 。 优先级队列的元素根据它们的有序natural ordering ，或由一个Comparator在队列构造的时候提供，这取决于所使用的构造方法。 优先队列不允许null元素。 依靠自然排序的优先级队列也不允许插入不可比较的对象（这样做可能导致ClassCastException ）。
  2.2、该队列的头部是相对于指定顺序的最小元素。 如果多个元素被绑定到最小值，那么头就是这些元素之一 - 关系被任意破坏。 队列检索操作poll ， remove ， peek和element访问在队列的头部的元件。
  2.3、优先级队列是无限制的，但是具有管理用于在队列上存储元素的数组的大小的内部容量 。 它始终至少与队列大小一样大。 当元素被添加到优先级队列中时，其容量会自动增长。 没有规定增长政策的细节。
  2.4、该类及其迭代器实现Collection和Iterator接口的所有可选方法。 方法iterator()中提供的迭代器不能保证以任何特定顺序遍历优先级队列的元素。 如果需要有序遍历，请考虑使用Arrays.sort(pq.toArray()) 。
  2.5、请注意，此实现不同步。 如果任何线程修改队列，多线程不应同时访问PriorityQueue实例。 而是使用线程安全的PriorityBlockingQueue类。
  **实现注意事项**：此实现提供了O（log（n））的时间入队和出队方法（ offer ， poll ， remove()和add ）; remove(Object)和contains(Object)方法的线性时间; 和恒定时间检索方法（ peek ， element和size ）。
3. `ConcurrentLinkedQueue`：基于链接节点的无界并发deque(deque是双端队列) 。 并发插入，删除和访问操作可以跨多个线程安全执行。 A ConcurrentLinkedDeque是许多线程将共享对公共集合的访问的适当选择。像大多数其他并发集合实现一样，此类不允许使用null元素。



#### 设`int x = 1; float y = 2;`，则表达式`x/y`的值是：（）
A. 0

B. 1

C. 2

D. 以上都不是

**答案**：D

**题目来源**：https://www.nowcoder.com/questionTerminal/0e96a198c7cc4d06a00ababae1bbbb0b

**解析**：根据基本类型的转换规则，当算术运算中，两个操作数中都不是double类型但是其中一个是float的时候，另一个操作数也会转为float类型，计算结果也是float类型。所以
`x / y = (float)1.0 / (float) 2.0 = 0.5(float类型的)`。

#### 关于static说法不正确的是（）
A. 可以直接用类名来访问类中的静态方法（public权限）

B. 静态块仅在类加载时执行一次。

C. static方法就是没有this的方法

D. 不可以用对象名来访问类中的静态方法（public权限）

** 答案 ** : D

** 题目来源**： https://www.nowcoder.com/profile/848042/myFollowings/detail/4016488

** 解析 ** ：栽在C项了，this就是当前调用对象，而静态是属于了类的，无法确定调用者，所以static里面就没有this的调用了。【看被人的回答有人得到C项的逆否命题：有this的就不是static方法，厉害了，666】。 D项实际上是可以用对象名来访问类中的静态方法的，只是那样就没有有意义而已，并且会抛出警告。


#### 下列关于管道（Pipe）通信的叙述中，正确的是（）
A. 进程对管道进行读操作和写操作都可能被组设

B. 一个管道只能有一个进行或一个写进程对其操作

C. 一个管道可实现双向数据传输

D. 管道的容量仅受磁盘容量大小限制


** 答案**： A

** 题目来源**: https://www.nowcoder.com/profile/848042/myFollowings/detail/4016483

** 题目解析 **： 还没有学到“管道通信”这个概念，这题目的解析先放下来吧。不懂得看链接。

#### Java8 中，忽略内部接口情况，不能用来修饰interface里的方法的有（）
A. private

B. public

C. protected

D. static

** 答案**： AC

** 题目来源**： https://www.nowcoder.com/profile/848042/myFollowings/detail/4016346

** 解析**： Java8 的接口方法可以有如下定义： only public, abstract, default, static and strictfp are permitted。 注意Java8开始支持接口中定义静态方法了。
```java
public interface InterfaceTest {
    public void fun1 ();

    abstract void fun2();

    static void fun3(){
        System.out.println("java 8 新特性");
    }

    default void fun4(){
        System.out.println("java 8 新特性");
    }
}
```
并且会发现在IDEA中，public和abstract修饰符会变灰，说明这是接口方法默认的两个修饰符。

另外注意题目问的是修饰接口中方法的修饰符，不是问修饰接口。那么修饰接口的修饰符可以有哪些？ 只能是public、abstract和什么都不写。abstract是默认的。那么为什么protected不能修饰接口呢？根据作者的意思《Java编程思想》，interface是一种极度抽象的类，如果用protected去修饰它，其作用范围仅仅是当前包内，和继承该类的包外对象，仔细一想，这个public没有什么区别，所以没有必要用protected。

static关键词不能用来修饰接口和主类（外部类），但是可以修饰外部类。

> 整理下 修饰符、 接口 、 抽象类的有关知识吧

#### 下面关于程序编译说法正确的是（）
A. Java语言是编译型语言，会把Java程序翻译成二进制指令直接运行

B. Java编译出来的目标文件与具体操作系统有关

C. Java是解释型语言，在运行时才进行翻译指令

D. Java编译出来的目标文件，可以运行在任意JVM上。

** 答案 ** : D

** 题目来源**: https://www.nowcoder.com/questionTerminal/dba570e6fed34c24a49fd827e9869e49

** 解析：**： 这道题的答案有问题吧。我觉得是C。Java是解释型语言这没错。D项是错的，高版本的JVM编译出来的目标文件无法在低版本的JVM上运行。



#### 指出下列程序运行的结果：
```java
public class Example{
    String str=new String("tarena");
    char[]ch={'a','b','c'};
    public static void main(String args[]){
        Example ex=new Example();
        ex.change(ex.str,ex.ch);
        System.out.print(ex.str+" and ");
        System.out.print(ex.ch);
    }
    public void change(String str,char ch[]){
   //引用类型变量，传递的是地址，属于引用传递。
        str="test ok";
        ch[0]='g';
    }
}
```
A. tarena and abc

B. tarena and gbc

C. test ok and abc

D. test ok and gbc

**答案** ： B

**题目来源** ： https://www.nowcoder.com/profile/848042/myFollowings/detail/4016332

**解析**: 哎，为什么这种题目遇到好多次了还是转不过弯来。首先明确一个概念啊，Java中只有值传递，没有引用传递。String 和 char 数组都是引用类型，传递的是地址，这样会影响原来变量的值，这跟引用传递很像，但是像归像，值传递和引用传递不是一个概念。另外，String是一个特殊的引用，为什么，因为字符串不可改变。所以题目中函数中的str变量和原来的str已经不是同一个东西了，它是一个局部引用，随着函数结束就没有了。方法中ch虽然也是一个副本，但是方法利用它修改了它所指向的字符数组中的第一个元素。方法结束后，所有的副本弹出结束。但是我们的成员变量str和ch还存在，他们依然是之前的地址，所以str的内容不会变，而ch的第一个元素被改变。

> 一定要记住Java中只有值传递，所有的参数只是一个副本！副本！副本！

#### 常用的servlet包的名称是（）
A. java.servlet

B. javax.servlet

C. servlet.http

D. javax.servlet.http

** 答案**： BD

** 题目来源**： https://www.nowcoder.com/profile/848042/myFollowings/detail/4016277

** 解析 **： 使用 Java 技术开发 WEB 应用程序 , 深入了解 Servlet 的机制对应用的开发将有重要的推动作用 . 而想深入了解 Servlet 的机制就不得不了解 javax.servlet 包 。javax.servlet 包中包含了 7 个接口 ,3 个类和 2 个异常类 , 它们分别是 :
* 接口 :RequestDispatcher,Servlet,ServletConfig,ServletContext,ServletRequest,ServletResponse 和 SingleThreadModel
* 类 :GenericServlet,ServletInputStream 和 ServletOutputStream
* 异常类 :ServletException 和 UnavailableException。

暂时还没有学习到这个包，先记下来吧。

#### Java用（）机制实现了进程之间的同步执行
A. 监视器

B. 虚拟机

C. 多个CPU

D. 异步调用

** 答案 **: A

** 题目来源**：https://www.nowcoder.com/questionTerminal/8312c75bc0b04f5a88511da1cc70972d

** 解析**： 在一个程序当中代码段访问了同一个对象从单独的并发的线程当中，那么这个代码段叫”临界区”

怎么解决呢：使用同步的机制对临界区进行保护

同步的两种方式：同步块和同步方法
对于同步来说都是使用synchronized方法
每一个对象都有一个监视器，或者叫做锁。

#### 如下代码，执行test()函数后，屏幕打印结果为（）
```java
public class Test2
{
    public void add(Byte b)
    {
        b = b++;
    }
    public void test()
    {
        Byte a = 127;
        Byte b = 127;
        add(++a);
        System.out.print(a + " ");
        add(b);
        System.out.print(b + "");
    }
}
```
A. 127 127
B. 128 127
C. 129 128
D. 以上都不对

** 答案 **： D

** 题目来源 **：https://www.nowcoder.com/questionTerminal/1bab09264a1c4528aa60ee9bca5f0976?toCommentId=675739

** 解析 **： 首先要注意的是Java中值传递的参数传递方式，所以记住调用add方法的时候，形参是实参的一份拷贝而已。OK，首先a是一个Byte型对象的引用，而这个类型的范围是[-128,127]，根据包装类自动装箱的原理，a和b实际上是同一个对象的引用。可以在b的声明后面打印一下`System.out.println(a == b)`发现打印出true。那么`add(++a)`这句话执行经历了什么过程呢？

首先看++a，首先会触发自动拆箱操作Byte.byteValue()方法，得到基本数值类型127，此时再进行+1的操作，根据基本数值类型间的转化规则我们知道，此时基本数据类型byte127会转为int型的127再进行+1操作，得到int型的128，然后再强制转换byte型，可是bye的范围是[-128,127]，所以强制转换的时候会有溢出，编程了byte型的-128，再触发自动装箱操作， 根据Byte自动装箱缓存的原理，此时Byte引用的是-128这个cache对象，不信的话在第一个System之前加入下面两句话：
```java
Byte c = -128;
System.out.println(a == c); //true
```
上面的这一个过程在经过反编译之后的字节码中得到验证：
```java

链接：https://www.nowcoder.com/questionTerminal/1bab09264a1c4528aa60ee9bca5f0976?toCommentId=675739
来源：牛客网

// 源代码
public static void main(String[] args) {
    Byte a = 127;
    ++a;
}
// 字节码
public static void main(java.lang.String[]);
    Code:
       0: bipush        127 // 将一个byte型常量值推送至操作数栈栈顶
       2: invokestatic  #2  // 自动装箱：访问栈顶元素，作为函数实参传入静态方法Byte.valueOf(byte)，    
                            // 返回value值为127的Byte对象的地址，并压栈
       5: astore_1          // 将栈顶数值赋值给局部变量表中下标为1的引用型局部变量a，栈顶数值出栈。此时a对应的byte值为127。
       6: aload_1           // 局部变量表中下标为1的引用型局部变量a进栈       
       7: invokevirtual #3  // 自动拆箱，访问栈顶元素a，调用实例方法a.byteValue获取a所指Byte
                            // 对象的value值，并压栈
      10: iconst_1          // int型常量值1进栈
      11: iadd              // 依次弹出栈顶两int型数值1(0000 0001)、127(0111 1111)
                            //（byte类型自动转型为int类型）相加，并将结果128(1000 0000)进栈
      12: i2b               // 栈顶int值128(1000 0000)出栈，强转成byte值-128(1000 0000)，并且结果进栈
      13: invokestatic  #2  // 自动装箱：访问栈顶元素，作为函数实参传入静态方法Byte.valueOf(byte)，
                            // 返回value值为-128的Byte对象的地址，并压栈
      16: astore_1          // 将栈顶数值赋值给局部变量表中下标为1的引用型局部变量a，栈顶数值出栈。此时a对应的byte值为-128。
      17: return
}
```
发现打印出的是true。这个时候这个引用作为实参传递给add方法，再次重申，Java中只有值传递，所以调用add方法的时候我们将对象的引用地址传递给了add方法的形参b。在add方法中，同样经历的拆箱、转为int、加1、强制转化、装箱的过程，`b = b ++`是不会改变b的引用的，因为先进行了赋值再进行了加法。而`b = ++b`则会改变b的引用的，这时候指向了-127的这个cache对象。add方法结束后这个b也就被销毁了。

所以这道题目打印的结果应该是"-128, 127"。

借着这道题，还有一个问题需要继续讨论一下，"++a"这种操作之后，是a的引用改变了还会说指向没变，但是指向的内容改变了。当然是指向改变了，下面这个测试程序就能说明问题了：
```java

Byte a = 127;
Byte b = a;
a++;
System.out.println(b == a); //false

Byte c = -128;
System.out.println(a == c); //true

```

注意了啊，** 包装类里面的value值都是final的，不能改变，只能改变引用**。

#### 给出以下代码，请给出结果：
```java
class Two{
    Byte x;
}
class PassO{
    public static void main(String[] args){
        PassO p=new PassO();
        p.start();
    }
    void start(){
        Two t=new Two();
        System.out.print(t.x+””);
        Two t2=fix(t);
        System.out.print(t.x+” ” +t2.x);
    }
    Two fix(Two tt){
        tt.x=42;
        return tt;
    }
}
```
A. null null 42

B. null 42 42

C. 0 0 42

D. 0 42 42

E. An exception is thrown at Runtime

F. Compliation


** 答案**：B

** 题目来源**：

**解析**：考察成员变量的默认值和值传递方法，需要的是类Two中成员变量是包装类`Byte`，是对象，初始值是null。

#### 下列选项中正确的方法声明的是?()
A. protected abstract void f1();

B. public final void f1(){}

C. static final void f1(){}

D. private void f1(){}

** 答案 **: ABCD

** 题目来源 **：

** 解析**：注意A项，抽象类中的抽象方法能够被private之外的修饰符修饰(abstract不能与private、static共存)，但是接口中的抽象方法默认且唯一的修饰词是`public abstract`。B项是不能被重写的方法。C项是静态且不能被重写的方法；D项是私有方法。

> 记住！ **abstract不能与final、private、static关键字共存！**

#### 下列不属于Java语言性特点的是（）
A. Java致力于检查程序在编译和运行时的错误

B. Java能运行虚拟机实现跨平台

C. Java自己操纵内存减少了内存出错的可能性

D. Java还实现了真数组，避免了覆盖数据类型的可能

** 答案 **： D

** 题目来源 **：

** 解析**: 真数组的定义是：数组元素在内存中是一个接着一个线性存放的，通过第一个元素就能访问随后的元素，避免了数据覆盖的可能性，和数据类型覆盖并没有关系。注意D项说法，真数组的避免数据覆盖的可能，而不是数据覆盖类型。

#### Given the following code,Which statement at line 11 constructs an instance of the inner class?()
```java
import EnclosingOne.InsideOne

class Enclosingone
{
    public class InsideOne {}
}
public class inertest
{
    public static void main(string[]args)
    {
        EnclosingOne eo = new EnclosingOne();
        //insert code here
    }

}
```
A. InsideOne ei=eo.new InsideOne();

B. eo.InsideOne ei=eo.new InsideOne();

C. InsideOne ei=EnclosingOne.new InsideOne();

D. EnclosingOne.InsideOne ei=eo.new InsideOne();

**答案**：AD

** 题目来源 ** ：https://www.nowcoder.com/questionTerminal/282aa74498f649cc81a41cb24ab1353e

** 解析 ** ：有了内部类的知识，D项没有问题。关键在于A，仔细看题目，import了内部类，所以A项也是对的。


#### What will happen when you attempt to compile and run the following code?()
```java
public class Test{
  static{
     int x=5;
  }

  static int x,y;

  public static void main(String args[]){
     x--;
     myMethod( );
     System.out.println(x+y+ ++x);
  }

  public static void myMethod( ){
    y=x++ + ++x;
   }
}
```
A. compiletime error

B. prints:1

C. prints:2

D. prints:3

E. prints:7

F. prints:8

**答案**：D

** 题目来源**：

** 解析 **：首先是加载顺序，先加载静态域，static代码块在前所以先执行，其中x是一个局部变量，代码块执行完毕后释放。接着初始化静态x和y，默认为0。然后进入main方法，x--执行后x变成-1;进行入myMethod方法，`y=x++ + ++x;`相当于`y=(x++)+(++x)`，当++或者--和其它变量进行运算时，x++表示先运算，再自增，++x表示先自增再参与运算。所以就时x为-1参与运算，然后自增，x此时为0，++x后x为1，然后参与运算，那么y=-1+1就为0，此时x为1。注意此时y是静态变量y而不是局部变量。执行并打印x+y + ++x运算方式和第5步相同，最后计算结果就为3。
